veet/__init__.py
veet/cli/__init__.py
veet/cli/application.py
veet/commands/FrameworkNew.py
veet/commands/Install.py
veet/commands/OsEnv.py
veet/commands/__init__.py
veet/core/__init__.py
veet/core/logging.py
veet/core/paths.py
veet/framework/__init__.py
veet/framework/application.py
veet/framework/commands/Serve.py
veet/framework/commands/__init__.py
veet/framework/routing/Route.py
veet/framework/routing/Routing.py
veet/framework/routing/__init__.py
veet/framework/server/__init__.py
veet-0.1.0.dist-info/entry_points.txt
veet-0.1.0.dist-info/WHEEL
veet-0.1.0.dist-info/METADATA
veet-0.1.0.dist-info/RECORD
